<annotation>
	<folder></folder>
	<filename>ABBY_023_2018_jpeg.rf.5e1f50d2e52106b99d48b4da2b5e1bbe.jpg</filename>
	<path>ABBY_023_2018_jpeg.rf.5e1f50d2e52106b99d48b4da2b5e1bbe.jpg</path>
	<source>
		<database>roboflow.ai</database>
	</source>
	<size>
		<width>416</width>
		<height>416</height>
		<depth>3</depth>
	</size>
	<segmented>0</segmented>
	<object>
		<name>tree-top</name>
		<pose>Unspecified</pose>
		<truncated>0</truncated>
		<difficult>0</difficult>
		<occluded>0</occluded>
		<bndbox>
			<xmin>50</xmin>
			<xmax>114</xmax>
			<ymin>56</ymin>
			<ymax>116</ymax>
		</bndbox>
	</object>
	<object>
		<name>tree-top</name>
		<pose>Unspecified</pose>
		<truncated>0</truncated>
		<difficult>0</difficult>
		<occluded>0</occluded>
		<bndbox>
			<xmin>99</xmin>
			<xmax>163</xmax>
			<ymin>222</ymin>
			<ymax>270</ymax>
		</bndbox>
	</object>
	<object>
		<name>tree-top</name>
		<pose>Unspecified</pose>
		<truncated>0</truncated>
		<difficult>0</difficult>
		<occluded>0</occluded>
		<bndbox>
			<xmin>284</xmin>
			<xmax>334</xmax>
			<ymin>33</ymin>
			<ymax>84</ymax>
		</bndbox>
	</object>
	<object>
		<name>tree-top</name>
		<pose>Unspecified</pose>
		<truncated>0</truncated>
		<difficult>0</difficult>
		<occluded>0</occluded>
		<bndbox>
			<xmin>308</xmin>
			<xmax>354</xmax>
			<ymin>307</ymin>
			<ymax>367</ymax>
		</bndbox>
	</object>
	<object>
		<name>tree-top</name>
		<pose>Unspecified</pose>
		<truncated>0</truncated>
		<difficult>0</difficult>
		<occluded>0</occluded>
		<bndbox>
			<xmin>242</xmin>
			<xmax>280</xmax>
			<ymin>75</ymin>
			<ymax>111</ymax>
		</bndbox>
	</object>
	<object>
		<name>tree-top</name>
		<pose>Unspecified</pose>
		<truncated>0</truncated>
		<difficult>0</difficult>
		<occluded>0</occluded>
		<bndbox>
			<xmin>334</xmin>
			<xmax>376</xmax>
			<ymin>57</ymin>
			<ymax>97</ymax>
		</bndbox>
	</object>
	<object>
		<name>tree-top</name>
		<pose>Unspecified</pose>
		<truncated>0</truncated>
		<difficult>0</difficult>
		<occluded>0</occluded>
		<bndbox>
			<xmin>383</xmin>
			<xmax>417</xmax>
			<ymin>112</ymin>
			<ymax>178</ymax>
		</bndbox>
	</object>
	<object>
		<name>tree-top</name>
		<pose>Unspecified</pose>
		<truncated>0</truncated>
		<difficult>0</difficult>
		<occluded>0</occluded>
		<bndbox>
			<xmin>24</xmin>
			<xmax>75</xmax>
			<ymin>105</ymin>
			<ymax>155</ymax>
		</bndbox>
	</object>
	<object>
		<name>tree-top</name>
		<pose>Unspecified</pose>
		<truncated>0</truncated>
		<difficult>0</difficult>
		<occluded>0</occluded>
		<bndbox>
			<xmin>312</xmin>
			<xmax>373</xmax>
			<ymin>131</ymin>
			<ymax>202</ymax>
		</bndbox>
	</object>
	<object>
		<name>tree-top</name>
		<pose>Unspecified</pose>
		<truncated>0</truncated>
		<difficult>0</difficult>
		<occluded>0</occluded>
		<bndbox>
			<xmin>177</xmin>
			<xmax>247</xmax>
			<ymin>366</ymin>
			<ymax>417</ymax>
		</bndbox>
	</object>
	<object>
		<name>tree-top</name>
		<pose>Unspecified</pose>
		<truncated>0</truncated>
		<difficult>0</difficult>
		<occluded>0</occluded>
		<bndbox>
			<xmin>86</xmin>
			<xmax>134</xmax>
			<ymin>358</ymin>
			<ymax>402</ymax>
		</bndbox>
	</object>
	<object>
		<name>tree-top</name>
		<pose>Unspecified</pose>
		<truncated>0</truncated>
		<difficult>0</difficult>
		<occluded>0</occluded>
		<bndbox>
			<xmin>2</xmin>
			<xmax>56</xmax>
			<ymin>339</ymin>
			<ymax>415</ymax>
		</bndbox>
	</object>
	<object>
		<name>tree-top</name>
		<pose>Unspecified</pose>
		<truncated>0</truncated>
		<difficult>0</difficult>
		<occluded>0</occluded>
		<bndbox>
			<xmin>3</xmin>
			<xmax>51</xmax>
			<ymin>146</ymin>
			<ymax>234</ymax>
		</bndbox>
	</object>
	<object>
		<name>tree-top</name>
		<pose>Unspecified</pose>
		<truncated>0</truncated>
		<difficult>0</difficult>
		<occluded>0</occluded>
		<bndbox>
			<xmin>133</xmin>
			<xmax>199</xmax>
			<ymin>1</ymin>
			<ymax>57</ymax>
		</bndbox>
	</object>
	<object>
		<name>tree-top</name>
		<pose>Unspecified</pose>
		<truncated>0</truncated>
		<difficult>0</difficult>
		<occluded>0</occluded>
		<bndbox>
			<xmin>129</xmin>
			<xmax>165</xmax>
			<ymin>171</ymin>
			<ymax>203</ymax>
		</bndbox>
	</object>
	<object>
		<name>tree-top</name>
		<pose>Unspecified</pose>
		<truncated>0</truncated>
		<difficult>0</difficult>
		<occluded>0</occluded>
		<bndbox>
			<xmin>192</xmin>
			<xmax>253</xmax>
			<ymin>108</ymin>
			<ymax>158</ymax>
		</bndbox>
	</object>
	<object>
		<name>tree-top</name>
		<pose>Unspecified</pose>
		<truncated>0</truncated>
		<difficult>0</difficult>
		<occluded>0</occluded>
		<bndbox>
			<xmin>81</xmin>
			<xmax>137</xmax>
			<ymin>290</ymin>
			<ymax>348</ymax>
		</bndbox>
	</object>
	<object>
		<name>tree-top</name>
		<pose>Unspecified</pose>
		<truncated>0</truncated>
		<difficult>0</difficult>
		<occluded>0</occluded>
		<bndbox>
			<xmin>376</xmin>
			<xmax>410</xmax>
			<ymin>238</ymin>
			<ymax>282</ymax>
		</bndbox>
	</object>
	<object>
		<name>tree-top</name>
		<pose>Unspecified</pose>
		<truncated>0</truncated>
		<difficult>0</difficult>
		<occluded>0</occluded>
		<bndbox>
			<xmin>54</xmin>
			<xmax>130</xmax>
			<ymin>3</ymin>
			<ymax>51</ymax>
		</bndbox>
	</object>
	<object>
		<name>tree-top</name>
		<pose>Unspecified</pose>
		<truncated>0</truncated>
		<difficult>0</difficult>
		<occluded>0</occluded>
		<bndbox>
			<xmin>357</xmin>
			<xmax>392</xmax>
			<ymin>325</ymin>
			<ymax>366</ymax>
		</bndbox>
	</object>
	<object>
		<name>tree-top</name>
		<pose>Unspecified</pose>
		<truncated>0</truncated>
		<difficult>0</difficult>
		<occluded>0</occluded>
		<bndbox>
			<xmin>211</xmin>
			<xmax>245</xmax>
			<ymin>249</ymin>
			<ymax>282</ymax>
		</bndbox>
	</object>
	<object>
		<name>tree-top</name>
		<pose>Unspecified</pose>
		<truncated>0</truncated>
		<difficult>0</difficult>
		<occluded>0</occluded>
		<bndbox>
			<xmin>165</xmin>
			<xmax>201</xmax>
			<ymin>324</ymin>
			<ymax>372</ymax>
		</bndbox>
	</object>
	<object>
		<name>tree-top</name>
		<pose>Unspecified</pose>
		<truncated>0</truncated>
		<difficult>0</difficult>
		<occluded>0</occluded>
		<bndbox>
			<xmin>205</xmin>
			<xmax>239</xmax>
			<ymin>164</ymin>
			<ymax>194</ymax>
		</bndbox>
	</object>
	<object>
		<name>tree-top</name>
		<pose>Unspecified</pose>
		<truncated>0</truncated>
		<difficult>0</difficult>
		<occluded>0</occluded>
		<bndbox>
			<xmin>119</xmin>
			<xmax>145</xmax>
			<ymin>59</ymin>
			<ymax>89</ymax>
		</bndbox>
	</object>
	<object>
		<name>tree-top</name>
		<pose>Unspecified</pose>
		<truncated>0</truncated>
		<difficult>0</difficult>
		<occluded>0</occluded>
		<bndbox>
			<xmin>115</xmin>
			<xmax>165</xmax>
			<ymin>101</ymin>
			<ymax>147</ymax>
		</bndbox>
	</object>
	<object>
		<name>tree-top</name>
		<pose>Unspecified</pose>
		<truncated>0</truncated>
		<difficult>0</difficult>
		<occluded>0</occluded>
		<bndbox>
			<xmin>267</xmin>
			<xmax>303</xmax>
			<ymin>259</ymin>
			<ymax>311</ymax>
		</bndbox>
	</object>
	<object>
		<name>tree-top</name>
		<pose>Unspecified</pose>
		<truncated>0</truncated>
		<difficult>0</difficult>
		<occluded>0</occluded>
		<bndbox>
			<xmin>218</xmin>
			<xmax>260</xmax>
			<ymin>281</ymin>
			<ymax>325</ymax>
		</bndbox>
	</object>
	<object>
		<name>tree-top</name>
		<pose>Unspecified</pose>
		<truncated>0</truncated>
		<difficult>0</difficult>
		<occluded>0</occluded>
		<bndbox>
			<xmin>308</xmin>
			<xmax>372</xmax>
			<ymin>239</ymin>
			<ymax>285</ymax>
		</bndbox>
	</object>
	<object>
		<name>tree-top</name>
		<pose>Unspecified</pose>
		<truncated>0</truncated>
		<difficult>0</difficult>
		<occluded>0</occluded>
		<bndbox>
			<xmin>131</xmin>
			<xmax>169</xmax>
			<ymin>312</ymin>
			<ymax>344</ymax>
		</bndbox>
	</object>
	<object>
		<name>tree-top</name>
		<pose>Unspecified</pose>
		<truncated>0</truncated>
		<difficult>0</difficult>
		<occluded>0</occluded>
		<bndbox>
			<xmin>93</xmin>
			<xmax>123</xmax>
			<ymin>181</ymin>
			<ymax>224</ymax>
		</bndbox>
	</object>
</annotation>
