<annotation>
	<folder></folder>
	<filename>ABBY_075_2019_jpeg.rf.7438d29cd7f182b3cbfcfbdf57400df1.jpg</filename>
	<path>ABBY_075_2019_jpeg.rf.7438d29cd7f182b3cbfcfbdf57400df1.jpg</path>
	<source>
		<database>roboflow.ai</database>
	</source>
	<size>
		<width>416</width>
		<height>416</height>
		<depth>3</depth>
	</size>
	<segmented>0</segmented>
	<object>
		<name>tree-top</name>
		<pose>Unspecified</pose>
		<truncated>0</truncated>
		<difficult>0</difficult>
		<occluded>0</occluded>
		<bndbox>
			<xmin>245</xmin>
			<xmax>285</xmax>
			<ymin>343</ymin>
			<ymax>383</ymax>
		</bndbox>
	</object>
	<object>
		<name>tree-top</name>
		<pose>Unspecified</pose>
		<truncated>0</truncated>
		<difficult>0</difficult>
		<occluded>0</occluded>
		<bndbox>
			<xmin>353</xmin>
			<xmax>397</xmax>
			<ymin>276</ymin>
			<ymax>317</ymax>
		</bndbox>
	</object>
	<object>
		<name>tree-top</name>
		<pose>Unspecified</pose>
		<truncated>0</truncated>
		<difficult>0</difficult>
		<occluded>0</occluded>
		<bndbox>
			<xmin>376</xmin>
			<xmax>412</xmax>
			<ymin>55</ymin>
			<ymax>87</ymax>
		</bndbox>
	</object>
	<object>
		<name>tree-top</name>
		<pose>Unspecified</pose>
		<truncated>0</truncated>
		<difficult>0</difficult>
		<occluded>0</occluded>
		<bndbox>
			<xmin>320</xmin>
			<xmax>363</xmax>
			<ymin>302</ymin>
			<ymax>347</ymax>
		</bndbox>
	</object>
	<object>
		<name>tree-top</name>
		<pose>Unspecified</pose>
		<truncated>0</truncated>
		<difficult>0</difficult>
		<occluded>0</occluded>
		<bndbox>
			<xmin>245</xmin>
			<xmax>279</xmax>
			<ymin>94</ymin>
			<ymax>128</ymax>
		</bndbox>
	</object>
	<object>
		<name>tree-top</name>
		<pose>Unspecified</pose>
		<truncated>0</truncated>
		<difficult>0</difficult>
		<occluded>0</occluded>
		<bndbox>
			<xmin>319</xmin>
			<xmax>353</xmax>
			<ymin>219</ymin>
			<ymax>253</ymax>
		</bndbox>
	</object>
	<object>
		<name>tree-top</name>
		<pose>Unspecified</pose>
		<truncated>0</truncated>
		<difficult>0</difficult>
		<occluded>0</occluded>
		<bndbox>
			<xmin>119</xmin>
			<xmax>155</xmax>
			<ymin>363</ymin>
			<ymax>403</ymax>
		</bndbox>
	</object>
	<object>
		<name>tree-top</name>
		<pose>Unspecified</pose>
		<truncated>0</truncated>
		<difficult>0</difficult>
		<occluded>0</occluded>
		<bndbox>
			<xmin>362</xmin>
			<xmax>404</xmax>
			<ymin>150</ymin>
			<ymax>192</ymax>
		</bndbox>
	</object>
	<object>
		<name>tree-top</name>
		<pose>Unspecified</pose>
		<truncated>0</truncated>
		<difficult>0</difficult>
		<occluded>0</occluded>
		<bndbox>
			<xmin>366</xmin>
			<xmax>397</xmax>
			<ymin>373</ymin>
			<ymax>407</ymax>
		</bndbox>
	</object>
	<object>
		<name>tree-top</name>
		<pose>Unspecified</pose>
		<truncated>0</truncated>
		<difficult>0</difficult>
		<occluded>0</occluded>
		<bndbox>
			<xmin>232</xmin>
			<xmax>270</xmax>
			<ymin>169</ymin>
			<ymax>205</ymax>
		</bndbox>
	</object>
	<object>
		<name>tree-top</name>
		<pose>Unspecified</pose>
		<truncated>0</truncated>
		<difficult>0</difficult>
		<occluded>0</occluded>
		<bndbox>
			<xmin>145</xmin>
			<xmax>195</xmax>
			<ymin>321</ymin>
			<ymax>371</ymax>
		</bndbox>
	</object>
	<object>
		<name>tree-top</name>
		<pose>Unspecified</pose>
		<truncated>0</truncated>
		<difficult>0</difficult>
		<occluded>0</occluded>
		<bndbox>
			<xmin>17</xmin>
			<xmax>59</xmax>
			<ymin>310</ymin>
			<ymax>352</ymax>
		</bndbox>
	</object>
	<object>
		<name>tree-top</name>
		<pose>Unspecified</pose>
		<truncated>0</truncated>
		<difficult>0</difficult>
		<occluded>0</occluded>
		<bndbox>
			<xmin>238</xmin>
			<xmax>276</xmax>
			<ymin>139</ymin>
			<ymax>171</ymax>
		</bndbox>
	</object>
	<object>
		<name>tree-top</name>
		<pose>Unspecified</pose>
		<truncated>0</truncated>
		<difficult>0</difficult>
		<occluded>0</occluded>
		<bndbox>
			<xmin>191</xmin>
			<xmax>221</xmax>
			<ymin>67</ymin>
			<ymax>97</ymax>
		</bndbox>
	</object>
	<object>
		<name>tree-top</name>
		<pose>Unspecified</pose>
		<truncated>0</truncated>
		<difficult>0</difficult>
		<occluded>0</occluded>
		<bndbox>
			<xmin>347</xmin>
			<xmax>383</xmax>
			<ymin>329</ymin>
			<ymax>367</ymax>
		</bndbox>
	</object>
	<object>
		<name>tree-top</name>
		<pose>Unspecified</pose>
		<truncated>0</truncated>
		<difficult>0</difficult>
		<occluded>0</occluded>
		<bndbox>
			<xmin>152</xmin>
			<xmax>188</xmax>
			<ymin>112</ymin>
			<ymax>147</ymax>
		</bndbox>
	</object>
	<object>
		<name>tree-top</name>
		<pose>Unspecified</pose>
		<truncated>0</truncated>
		<difficult>0</difficult>
		<occluded>0</occluded>
		<bndbox>
			<xmin>105</xmin>
			<xmax>135</xmax>
			<ymin>397</ymin>
			<ymax>417</ymax>
		</bndbox>
	</object>
	<object>
		<name>tree-top</name>
		<pose>Unspecified</pose>
		<truncated>0</truncated>
		<difficult>0</difficult>
		<occluded>0</occluded>
		<bndbox>
			<xmin>136</xmin>
			<xmax>169</xmax>
			<ymin>7</ymin>
			<ymax>39</ymax>
		</bndbox>
	</object>
	<object>
		<name>tree-top</name>
		<pose>Unspecified</pose>
		<truncated>0</truncated>
		<difficult>0</difficult>
		<occluded>0</occluded>
		<bndbox>
			<xmin>382</xmin>
			<xmax>416</xmax>
			<ymin>350</ymin>
			<ymax>379</ymax>
		</bndbox>
	</object>
	<object>
		<name>tree-top</name>
		<pose>Unspecified</pose>
		<truncated>0</truncated>
		<difficult>0</difficult>
		<occluded>0</occluded>
		<bndbox>
			<xmin>373</xmin>
			<xmax>417</xmax>
			<ymin>316</ymin>
			<ymax>359</ymax>
		</bndbox>
	</object>
	<object>
		<name>tree-top</name>
		<pose>Unspecified</pose>
		<truncated>0</truncated>
		<difficult>0</difficult>
		<occluded>0</occluded>
		<bndbox>
			<xmin>396</xmin>
			<xmax>417</xmax>
			<ymin>263</ymin>
			<ymax>302</ymax>
		</bndbox>
	</object>
	<object>
		<name>tree-top</name>
		<pose>Unspecified</pose>
		<truncated>0</truncated>
		<difficult>0</difficult>
		<occluded>0</occluded>
		<bndbox>
			<xmin>91</xmin>
			<xmax>127</xmax>
			<ymin>52</ymin>
			<ymax>86</ymax>
		</bndbox>
	</object>
	<object>
		<name>tree-top</name>
		<pose>Unspecified</pose>
		<truncated>0</truncated>
		<difficult>0</difficult>
		<occluded>0</occluded>
		<bndbox>
			<xmin>375</xmin>
			<xmax>417</xmax>
			<ymin>17</ymin>
			<ymax>57</ymax>
		</bndbox>
	</object>
	<object>
		<name>tree-top</name>
		<pose>Unspecified</pose>
		<truncated>0</truncated>
		<difficult>0</difficult>
		<occluded>0</occluded>
		<bndbox>
			<xmin>384</xmin>
			<xmax>417</xmax>
			<ymin>88</ymin>
			<ymax>129</ymax>
		</bndbox>
	</object>
	<object>
		<name>tree-top</name>
		<pose>Unspecified</pose>
		<truncated>0</truncated>
		<difficult>0</difficult>
		<occluded>0</occluded>
		<bndbox>
			<xmin>3</xmin>
			<xmax>43</xmax>
			<ymin>266</ymin>
			<ymax>302</ymax>
		</bndbox>
	</object>
	<object>
		<name>tree-top</name>
		<pose>Unspecified</pose>
		<truncated>0</truncated>
		<difficult>0</difficult>
		<occluded>0</occluded>
		<bndbox>
			<xmin>119</xmin>
			<xmax>156</xmax>
			<ymin>111</ymin>
			<ymax>147</ymax>
		</bndbox>
	</object>
	<object>
		<name>tree-top</name>
		<pose>Unspecified</pose>
		<truncated>0</truncated>
		<difficult>0</difficult>
		<occluded>0</occluded>
		<bndbox>
			<xmin>1</xmin>
			<xmax>20</xmax>
			<ymin>295</ymin>
			<ymax>328</ymax>
		</bndbox>
	</object>
	<object>
		<name>tree-top</name>
		<pose>Unspecified</pose>
		<truncated>0</truncated>
		<difficult>0</difficult>
		<occluded>0</occluded>
		<bndbox>
			<xmin>2</xmin>
			<xmax>26</xmax>
			<ymin>175</ymin>
			<ymax>207</ymax>
		</bndbox>
	</object>
	<object>
		<name>tree-top</name>
		<pose>Unspecified</pose>
		<truncated>0</truncated>
		<difficult>0</difficult>
		<occluded>0</occluded>
		<bndbox>
			<xmin>299</xmin>
			<xmax>347</xmax>
			<ymin>355</ymin>
			<ymax>403</ymax>
		</bndbox>
	</object>
	<object>
		<name>tree-top</name>
		<pose>Unspecified</pose>
		<truncated>0</truncated>
		<difficult>0</difficult>
		<occluded>0</occluded>
		<bndbox>
			<xmin>14</xmin>
			<xmax>42</xmax>
			<ymin>154</ymin>
			<ymax>186</ymax>
		</bndbox>
	</object>
	<object>
		<name>tree-top</name>
		<pose>Unspecified</pose>
		<truncated>0</truncated>
		<difficult>0</difficult>
		<occluded>0</occluded>
		<bndbox>
			<xmin>279</xmin>
			<xmax>311</xmax>
			<ymin>89</ymin>
			<ymax>120</ymax>
		</bndbox>
	</object>
	<object>
		<name>tree-top</name>
		<pose>Unspecified</pose>
		<truncated>0</truncated>
		<difficult>0</difficult>
		<occluded>0</occluded>
		<bndbox>
			<xmin>21</xmin>
			<xmax>66</xmax>
			<ymin>381</ymin>
			<ymax>417</ymax>
		</bndbox>
	</object>
	<object>
		<name>tree-top</name>
		<pose>Unspecified</pose>
		<truncated>0</truncated>
		<difficult>0</difficult>
		<occluded>0</occluded>
		<bndbox>
			<xmin>1</xmin>
			<xmax>24</xmax>
			<ymin>25</ymin>
			<ymax>96</ymax>
		</bndbox>
	</object>
	<object>
		<name>tree-top</name>
		<pose>Unspecified</pose>
		<truncated>0</truncated>
		<difficult>0</difficult>
		<occluded>0</occluded>
		<bndbox>
			<xmin>122</xmin>
			<xmax>149</xmax>
			<ymin>78</ymin>
			<ymax>105</ymax>
		</bndbox>
	</object>
	<object>
		<name>tree-top</name>
		<pose>Unspecified</pose>
		<truncated>0</truncated>
		<difficult>0</difficult>
		<occluded>0</occluded>
		<bndbox>
			<xmin>217</xmin>
			<xmax>249</xmax>
			<ymin>73</ymin>
			<ymax>105</ymax>
		</bndbox>
	</object>
	<object>
		<name>tree-top</name>
		<pose>Unspecified</pose>
		<truncated>0</truncated>
		<difficult>0</difficult>
		<occluded>0</occluded>
		<bndbox>
			<xmin>128</xmin>
			<xmax>181</xmax>
			<ymin>113</ymin>
			<ymax>149</ymax>
		</bndbox>
	</object>
	<object>
		<name>tree-top</name>
		<pose>Unspecified</pose>
		<truncated>0</truncated>
		<difficult>0</difficult>
		<occluded>0</occluded>
		<bndbox>
			<xmin>232</xmin>
			<xmax>270</xmax>
			<ymin>147</ymin>
			<ymax>186</ymax>
		</bndbox>
	</object>
	<object>
		<name>tree-top</name>
		<pose>Unspecified</pose>
		<truncated>0</truncated>
		<difficult>0</difficult>
		<occluded>0</occluded>
		<bndbox>
			<xmin>351</xmin>
			<xmax>391</xmax>
			<ymin>340</ymin>
			<ymax>393</ymax>
		</bndbox>
	</object>
	<object>
		<name>tree-top</name>
		<pose>Unspecified</pose>
		<truncated>0</truncated>
		<difficult>0</difficult>
		<occluded>0</occluded>
		<bndbox>
			<xmin>196</xmin>
			<xmax>222</xmax>
			<ymin>33</ymin>
			<ymax>61</ymax>
		</bndbox>
	</object>
	<object>
		<name>tree-top</name>
		<pose>Unspecified</pose>
		<truncated>0</truncated>
		<difficult>0</difficult>
		<occluded>0</occluded>
		<bndbox>
			<xmin>190</xmin>
			<xmax>232</xmax>
			<ymin>1</ymin>
			<ymax>40</ymax>
		</bndbox>
	</object>
	<object>
		<name>tree-top</name>
		<pose>Unspecified</pose>
		<truncated>0</truncated>
		<difficult>0</difficult>
		<occluded>0</occluded>
		<bndbox>
			<xmin>331</xmin>
			<xmax>367</xmax>
			<ymin>50</ymin>
			<ymax>85</ymax>
		</bndbox>
	</object>
	<object>
		<name>tree-top</name>
		<pose>Unspecified</pose>
		<truncated>0</truncated>
		<difficult>0</difficult>
		<occluded>0</occluded>
		<bndbox>
			<xmin>38</xmin>
			<xmax>72</xmax>
			<ymin>259</ymin>
			<ymax>294</ymax>
		</bndbox>
	</object>
	<object>
		<name>tree-top</name>
		<pose>Unspecified</pose>
		<truncated>0</truncated>
		<difficult>0</difficult>
		<occluded>0</occluded>
		<bndbox>
			<xmin>300</xmin>
			<xmax>332</xmax>
			<ymin>181</ymin>
			<ymax>225</ymax>
		</bndbox>
	</object>
</annotation>
